autoscrum/__init__.py
autoscrum/__main__.py
autoscrum/autoscrum.py
autoscrum/controller.py
autoscrum/data/acceptance.hbs
autoscrum/data/clarifier.hbs
autoscrum/data/featurizer.hbs
autoscrum/data/goalmaker.hbs
autoscrum/data/planner.hbs
autoscrum/data/requalizer.hbs
autoscrum/data/storylizer.hbs
autoscrum/data/taskalizer.hbs
autoscrum-0.3.0.dist-info/LICENSE
autoscrum-0.3.0.dist-info/METADATA
autoscrum-0.3.0.dist-info/WHEEL
autoscrum-0.3.0.dist-info/entry_points.txt
autoscrum-0.3.0.dist-info/top_level.txt
autoscrum-0.3.0.dist-info/RECORD
