Metadata-Version: 2.1
Name: autoscrum
Version: 0.3.0
Summary: AutoScrum
Author-email: Martin Schröder <info@swedishembedded.com>
License: GNU GENERAL PUBLIC LICENSE
Project-URL: Homepage, https://github.com/autoscrum/autoscrum
Classifier: License :: OSI Approved :: GNU General Public License v3 (GPLv3)
Classifier: Programming Language :: Python
Classifier: Programming Language :: Python :: 3
Requires-Python: >=3.9
License-File: LICENSE
Requires-Dist: guidance
Requires-Dist: pathlib
Requires-Dist: datetime
Provides-Extra: dev
Requires-Dist: black ; extra == 'dev'
Requires-Dist: build ; extra == 'dev'
Requires-Dist: bumpversion ; extra == 'dev'
Requires-Dist: isort ; extra == 'dev'
Requires-Dist: pip-tools ; extra == 'dev'
Requires-Dist: pytest ; extra == 'dev'
